docs/conf.py
graphite_render/__init__.py
graphite_render/app.py
graphite_render/carbonlink.py
graphite_render/config.py
graphite_render/encoders.py
graphite_render/evaluator.py
graphite_render/functions.py
graphite_render/intervals.py
graphite_render/middleware.py
graphite_render/node.py
graphite_render/readers.py
graphite_render/storage.py
graphite_render/utils.py
graphite_render/_vendor/__init__.py
graphite_render/_vendor/whisper.py
graphite_render/finders/__init__.py
graphite_render/finders/whisper.py
graphite_render/render/__init__.py
graphite_render/render/attime.py
graphite_render/render/datalib.py
graphite_render/render/glyph.py
graphite_render/render/grammar.py
graphite_render-1.1.8.dist-info/licenses/LICENSE
graphite_render-1.1.8.dist-info/METADATA
graphite_render-1.1.8.dist-info/WHEEL
graphite_render-1.1.8.dist-info/top_level.txt
graphite_render-1.1.8.dist-info/RECORD
