Metadata-Version: 2.4
Name: graphite-render
Version: 1.1.8
Summary: based on graphite-api, which is based graphite-web, but maintained for python3.
Author-email: Bruno Renié <bruno@renie.fr>, Christoph Settgast <csett86_git@quicksands.de>
License-Expression: Apache-2.0
Project-URL: Homepage, https://github.com/csett86/graphite-render
Project-URL: Repository, https://github.com/csett86/graphite-render
Keywords: graphite,api,monitoring,visualization
Classifier: Development Status :: 6 - Mature
Classifier: Environment :: Web Environment
Classifier: Framework :: Flask
Classifier: Intended Audience :: Developers
Classifier: Intended Audience :: System Administrators
Classifier: Operating System :: OS Independent
Classifier: Programming Language :: Python
Classifier: Programming Language :: Python :: 3
Classifier: Programming Language :: Python :: 3.9
Classifier: Programming Language :: Python :: 3.10
Classifier: Programming Language :: Python :: 3.11
Classifier: Programming Language :: Python :: 3.12
Classifier: Programming Language :: Python :: 3.13
Classifier: Programming Language :: Python :: 3.14
Classifier: Topic :: Scientific/Engineering :: Information Analysis
Classifier: Topic :: Scientific/Engineering :: Visualization
Classifier: Topic :: System :: Monitoring
Requires-Python: >=3.9
License-File: LICENSE
Requires-Dist: Flask
Requires-Dist: PyYAML
Requires-Dist: cairocffi
Requires-Dist: pyparsing>=3.0.0
Requires-Dist: structlog
Requires-Dist: tzlocal
Provides-Extra: sentry
Requires-Dist: raven[flask]; extra == "sentry"
Provides-Extra: cyanite
Requires-Dist: cyanite; extra == "cyanite"
Provides-Extra: cache
Requires-Dist: flask-caching; extra == "cache"
Provides-Extra: statsd
Requires-Dist: statsd; extra == "statsd"
Dynamic: license-file
